<annotation>
    <folder>deer</folder>
    <filename>Scoutvision-infrared-monocular-camera-mule-deer-buck-photo-by-Lea-Leggitt.jpg</filename>
    <size>
        <width>634</width>
        <height>476</height>
        <depth>3</depth>
    </size>
    <segmented>0</segmented>
    <object>
        <name>deer</name>
        <pose>Unspecified</pose>
        <truncated>0</truncated>
        <occluded>0</occluded>
        <difficult>0</difficult>
        <bndbox>
            <xmin>221</xmin>
            <ymin>192</ymin>
            <xmax>361</xmax>
            <ymax>439</ymax>
        </bndbox>
    </object>
</annotation>