<annotation>
    <folder>cleaned_training_photos</folder>
    <filename>housecat-A3AD4518-E9BC-4210-A54E-28B445F11C44.jpg</filename>
    <size>
        <width>259</width>
        <height>194</height>
        <depth>3</depth>
    </size>
    <segmented>0</segmented>
    <object>
        <name>house cat</name>
        <pose>Unspecified</pose>
        <truncated>0</truncated>
        <occluded>0</occluded>
        <difficult>0</difficult>
        <bndbox>
            <xmin>55</xmin>
            <ymin>61</ymin>
            <xmax>259</xmax>
            <ymax>174</ymax>
        </bndbox>
    </object>
</annotation>