<annotation>
    <folder>mountain lion</folder>
    <filename>images (4).jpeg</filename>
    <size>
        <width>300</width>
        <height>168</height>
        <depth>3</depth>
    </size>
    <segmented>0</segmented>
    <object>
        <name>mountain lion</name>
        <pose>Unspecified</pose>
        <truncated>0</truncated>
        <occluded>0</occluded>
        <difficult>0</difficult>
        <bndbox>
            <xmin>197</xmin>
            <ymin>93</ymin>
            <xmax>261</xmax>
            <ymax>131</ymax>
        </bndbox>
    </object>
    <object>
        <name>deer</name>
        <pose>Unspecified</pose>
        <truncated>0</truncated>
        <occluded>0</occluded>
        <difficult>0</difficult>
        <bndbox>
            <xmin>145</xmin>
            <ymin>38</ymin>
            <xmax>203</xmax>
            <ymax>97</ymax>
        </bndbox>
    </object>
    <object>
        <name>deer</name>
        <pose>Unspecified</pose>
        <truncated>0</truncated>
        <occluded>0</occluded>
        <difficult>0</difficult>
        <bndbox>
            <xmin>16</xmin>
            <ymin>47</ymin>
            <xmax>123</xmax>
            <ymax>150</ymax>
        </bndbox>
    </object>
</annotation>